codenerix_payments/__init__.py
codenerix_payments/admin.py
codenerix_payments/apps.py
codenerix_payments/forms.py
codenerix_payments/helpers.py
codenerix_payments/models.py
codenerix_payments/urls.py
codenerix_payments/views.py
codenerix_payments/locale/en/LC_MESSAGES/django.po
codenerix_payments/locale/es/LC_MESSAGES/django.mo
codenerix_payments/locale/es/LC_MESSAGES/django.po
codenerix_payments/management/__init__.py
codenerix_payments/management/__pycache__/__init__.cpython-310.pyc
codenerix_payments/management/__pycache__/__init__.cpython-35.pyc
codenerix_payments/management/__pycache__/__init__.cpython-39.pyc
codenerix_payments/management/commands/__init__.py
codenerix_payments/management/commands/paypal_test.py
codenerix_payments/management/commands/redsys_test.py
codenerix_payments/migrations/0001_initial.py
codenerix_payments/migrations/0002_auto_20190109_0752.py
codenerix_payments/migrations/0003_auto_20190806_0808.py
codenerix_payments/migrations/0004_paymentrequest_user.py
codenerix_payments/migrations/0005_paymentrequest_feedback.py
codenerix_payments/migrations/0006_auto_20190827_0759.py
codenerix_payments/migrations/0007_auto_20200429_1331.py
codenerix_payments/migrations/0008_auto_20200504_1145.py
codenerix_payments/migrations/0009_auto_20200706_1013.py
codenerix_payments/migrations/0010_auto_20200706_1032.py
codenerix_payments/migrations/0011_alter_currency_price_alter_paymentrequest_reverse_and_more.py
codenerix_payments/migrations/0012_alter_currency_price_alter_paymentrequest_total.py
codenerix_payments/migrations/0013_alter_paymentrequest_feedback_and_more.py
codenerix_payments/migrations/0014_alter_paymentrequest_order_ref.py
codenerix_payments/migrations/0015_alter_paymentrequest_order.py
codenerix_payments/migrations/0016_alter_paymentrequest_order_ref_and_more.py
codenerix_payments/migrations/0017_alter_paymentrequest_locator.py
codenerix_payments/migrations/__init__.py
codenerix_payments/migrations/__pycache__/0001_initial.cpython-310.pyc
django_codenerix_payments-4.0.8.dist-info/LICENSE
django_codenerix_payments-4.0.8.dist-info/METADATA
django_codenerix_payments-4.0.8.dist-info/WHEEL
django_codenerix_payments-4.0.8.dist-info/top_level.txt
django_codenerix_payments-4.0.8.dist-info/RECORD
