Metadata-Version: 2.1
Name: django-codenerix-payments
Version: 4.0.8
Summary: Codenerix Payments is a module that enables CODENERIX to manage payments and let clients to pay online.
Home-page: https://github.com/codenerix/django-codenerix-payments
Author: Juan Miguel Taboada Godoy <juanmi@juanmitaboada.com>, Juan Soler Ruiz <soleronline@gmail.com>
License: Apache License Version 2.0
Keywords: django,codenerix,management,erp,crm,payments
Platform: OS Independent
Classifier: Environment :: Web Environment
Classifier: Framework :: Django
Classifier: Framework :: Django :: 4.0
Classifier: Intended Audience :: Developers
Classifier: License :: Other/Proprietary License
Classifier: Operating System :: OS Independent
Classifier: Programming Language :: Python
Classifier: Programming Language :: Python :: 3.5
Classifier: Programming Language :: Python :: 3.6
Classifier: Programming Language :: Python :: 3.7
Classifier: Programming Language :: Python :: 3.8
Classifier: Programming Language :: Python :: 3.9
Classifier: Topic :: Internet :: WWW/HTTP
Classifier: Topic :: Internet :: WWW/HTTP :: Dynamic Content
License-File: LICENSE
Requires-Dist: cryptography
Requires-Dist: django-codenerix (>=5.0.23)
Requires-Dist: oss2
Requires-Dist: paypalrestsdk
Requires-Dist: rsa
Requires-Dist: yop-python-sdk (>=4.3.0)
